anudeepseuclidean/__init__.py
anudeepseuclidean-0.2.dist-info/METADATA
anudeepseuclidean-0.2.dist-info/WHEEL
anudeepseuclidean-0.2.dist-info/top_level.txt
anudeepseuclidean-0.2.dist-info/RECORD
