Metadata-Version: 2.1
Name: anudeepseuclidean
Version: 0.2
Summary: A simple Euclidean distance calculator
Author: Anudeep Errabelly
Author-email: errabellyanudeep@gmail.com
Classifier: Programming Language :: Python :: 3
Classifier: License :: OSI Approved :: MIT License
Classifier: Operating System :: OS Independent
Requires-Python: >=3.6
